magame/__init__.py
magame/all_mazes.py
magame/play_mappy.py
magame/play_pacman.py
magame/setup.py
magame/icons/brick.png
magame/icons/dot.png
magame/icons/meowky1.png
magame/icons/meowky2.png
magame/icons/mouse.png
magame/icons/pacman_down.png
magame/icons/pacman_left.png
magame/icons/pacman_right.png
magame/icons/pacman_up.png
magame-0.0.6.dist-info/METADATA
magame-0.0.6.dist-info/WHEEL
magame-0.0.6.dist-info/top_level.txt
magame-0.0.6.dist-info/RECORD
