Metadata-Version: 2.1
Name: magame
Version: 0.0.6
Summary: Write your own function to solve the maze!
Home-page: https://github.com/XiongPengNUS/magame
Author: Peng Xiong
Author-email: xiongpengnus@gmail.com
License: UNKNOWN
Platform: UNKNOWN
Classifier: Programming Language :: Python :: 3
Classifier: Operating System :: OS Independent
